pymbend/__init__.py
pymbend/mbend.py
pymbend/rayleigh.py
pymbend-0.1.0.dist-info/METADATA
pymbend-0.1.0.dist-info/WHEEL
pymbend-0.1.0.dist-info/licenses/LICENSE.txt
pymbend-0.1.0.dist-info/RECORD
