Metadata-Version: 2.3
Name: pymbend
Version: 0.1.0
Summary: Bending non-positive-definite matrices to positive-definite
Author-email: Michael Zietz <michael.zietz@gmail.com>
License-File: LICENSE.txt
Requires-Python: >=3.8
Requires-Dist: numpy>=1.26.4
